{"markdown": "Markdown", "githubpages": "GitHub Pages", "jetbrains": "JetBrains", "socketdotio": "Socket.io", "pandas": "pandas", "androidstudio": "Android Studio", "xcode": "Xcode", "cocoapods": "CocoaPods", "powershell": "PowerShell", "amazonaws": "Amazon AWS", "vuedotjs": "Vue.js", "windows": "Windows", "tmux": "tmux", "webpack": "Webpack", "chartdotjs": "Chart.js", "docker": "Docker", "cplusplus": "C++", "vim": "Vim", "css3": "CSS3", "swift": "Swift", "java": "Java", "react": "React", "jquery": "jQuery", "intellijidea": "IntelliJ IDEA", "django": "Django", "postgresql": "PostgreSQL", "less": "Less", "obsstudio": "OBS Studio", "kotlin": "Kotlin", "flask": "Flask", "gnubash": "GNU Bash", "datagrip": "DataGrip", "csharp": "C Sharp", "github": "GitHub", "spacemacs": "Spacemacs", "go": "Go", "nginx": "NGINX", "numpy": "NumPy", "javascript": "JavaScript", "webstorm": "WebStorm", "trello": "Trello", "ubuntu": "Ubuntu", "jupyter": "Jupyter", "android": "Android", "npm": "npm", "c": "C", "overleaf": "Overleaf", "bootstrap": "Bootstrap", "jinja": "Jinja", "githubactions": "GitHub Actions", "clion": "CLion", "html5": "HTML5", "pytest": "Pytest", "visualstudiocode": "Visual Studio Code", "linkedin": "LinkedIn", "nodedotjs": "Node.js", "latex": "LaTeX", "python": "Python", "macos": "macOS", "cmake": "CMake", "gitlab": "GitLab", "git": "Git", "sqlite": "SQLite", "slack": "Slack", "pycharm": "PyCharm", "pug": "Pug", "gnuemacs": "GNU Emacs"}